wiz_message/__init__.py
wiz_message/bot_client.py
wiz_message/elements.py
wiz_message/message.py
wiz_message-2.0.5.dist-info/METADATA
wiz_message-2.0.5.dist-info/WHEEL
wiz_message-2.0.5.dist-info/top_level.txt
wiz_message-2.0.5.dist-info/RECORD
